LICENSE
MANIFEST.in
README.rst
setup.cfg
setup.py
classification/__init__.py
classification/classification.py
classification/classificationproxy.py
classification/entities.py
classification/exceptions.py
classification/payloadconverters.py
classification/sessionutils.py
classification/types.py
classification/utils.py
docs/Makefile
docs/about_project.rst
docs/api_doc.rst
docs/conf.py
docs/getting_started.rst
docs/index.rst
docs/key_features.rst
docs/make.bat
docs/requirements.txt
docs/_static/.keep
docs/_templates/logo.html
fit_classification.egg-info/PKG-INFO
fit_classification.egg-info/SOURCES.txt
fit_classification.egg-info/dependency_links.txt
fit_classification.egg-info/not-zip-safe
fit_classification.egg-info/requires.txt
fit_classification.egg-info/top_level.txt
tests/test_entities.py
tests/test_http.py
tests/test_payload_converters.py
tests/test_token_saving.py
tests/test_utils.py
tests/fixtures/cassettes/test_http.test_demo_fail_401.json
tests/fixtures/cassettes/test_http.test_demo_success.json