Metadata-Version: 1.1
Name: fit-classification
Version: 0.1.1
Summary: Access Classification portal API from your Python programs
Home-page: https://github.com/145k0v/classification-python
Author: Boris Laskov
Author-email: laskobor@fit.cvut.cz
License: MIT License
Keywords: CTU FIT,Classification,coursework
Platform: UNKNOWN
Classifier: Intended Audience :: Developers
Classifier: License :: OSI Approved :: MIT License
Classifier: Operating System :: OS Independent
Classifier: Programming Language :: Python
Classifier: Programming Language :: Python :: Implementation :: CPython
Classifier: Programming Language :: Python :: 3
Classifier: Programming Language :: Python :: 3.6
Classifier: Topic :: Software Development :: Libraries
Classifier: Environment :: Console
